loguru_logging_intercept.py
loguru_logging_intercept-0.1.5.dist-info/LICENSE
loguru_logging_intercept-0.1.5.dist-info/METADATA
loguru_logging_intercept-0.1.5.dist-info/WHEEL
loguru_logging_intercept-0.1.5.dist-info/top_level.txt
loguru_logging_intercept-0.1.5.dist-info/RECORD
