Metadata-Version: 2.1
Name: loguru-logging-intercept
Version: 0.1.5
Summary: Code to integrate Loguru with Python's standard logging module
Home-page: https://github.com/MatthewScholefield/loguru-logging-intercept
Author: Matthew D. Scholefield
Author-email: matthew331199@gmail.com
Keywords: loguru logging intercept
Classifier: Development Status :: 3 - Alpha
Classifier: Intended Audience :: Developers
Classifier: Programming Language :: Python :: 3
Classifier: Programming Language :: Python :: 3.4
Classifier: Programming Language :: Python :: 3.5
Classifier: Programming Language :: Python :: 3.6
Classifier: Programming Language :: Python :: 3.7
Classifier: Programming Language :: Python :: 3.8
Classifier: Programming Language :: Python :: 3.9
Classifier: Programming Language :: Python :: 3.10
Classifier: Programming Language :: Python :: 3.11
Classifier: Programming Language :: Python :: 3.12
Classifier: Programming Language :: Python :: 3.13
License-File: LICENSE
Requires-Dist: loguru
